aws_secure_bucket/__init__.py
aws_secure_bucket/py.typed
aws_secure_bucket/_jsii/__init__.py
aws_secure_bucket/_jsii/aws-secure-bucket@0.7.1.jsii.tgz
aws_secure_bucket-0.7.1.dist-info/LICENSE
aws_secure_bucket-0.7.1.dist-info/METADATA
aws_secure_bucket-0.7.1.dist-info/WHEEL
aws_secure_bucket-0.7.1.dist-info/top_level.txt
aws_secure_bucket-0.7.1.dist-info/RECORD
